MANIFEST.in
README
setup.py
receipts/__init__.py
receipts/certs.py
receipts/fx.py
receipts/receipts.py
receipts.egg-info/PKG-INFO
receipts.egg-info/SOURCES.txt
receipts.egg-info/dependency_links.txt
receipts.egg-info/entry_points.txt
receipts.egg-info/not-zip-safe
receipts.egg-info/requires.txt
receipts.egg-info/top_level.txt
tests/__init__.py
tests/samples.py
tests/test.py