Metadata-Version: 1.0
Name: receipts
Version: 0.2.10
Summary: Verify web app receipts
Home-page: https://github.com/andymckay/receipts
Author: Andy McKay
Author-email: andym@mozilla.com
License: BSD
Platform: UNKNOWN
Classifier: Intended Audience :: Developers
Classifier: Natural Language :: English
Classifier: Operating System :: OS Independent
